bio2bel_interpro/__init__.py
bio2bel_interpro/__main__.py
bio2bel_interpro/cli.py
bio2bel_interpro/constants.py
bio2bel_interpro/enrich.py
bio2bel_interpro/manager.py
bio2bel_interpro/models.py
bio2bel_interpro/serialize.py
bio2bel_interpro/web.py
bio2bel_interpro/parser/__init__.py
bio2bel_interpro/parser/entries.py
bio2bel_interpro/parser/interpro_to_go.py
bio2bel_interpro/parser/proteins.py
bio2bel_interpro/parser/tree.py
bio2bel_interpro-0.2.1.dist-info/AUTHORS.rst
bio2bel_interpro-0.2.1.dist-info/LICENSE
bio2bel_interpro-0.2.1.dist-info/METADATA
bio2bel_interpro-0.2.1.dist-info/WHEEL
bio2bel_interpro-0.2.1.dist-info/entry_points.txt
bio2bel_interpro-0.2.1.dist-info/top_level.txt
bio2bel_interpro-0.2.1.dist-info/RECORD
