Metadata-Version: 2.1
Name: bio2bel-interpro
Version: 0.2.1
Summary: A package for converting InterPro to BEL
Home-page: https://github.com/bio2bel/interpro
Author: Charles Tapley Hoyt
Author-email: charles.hoyt@scai.fraunhofer.de
Maintainer: Charles Tapley Hoyt
Maintainer-email: charles.hoyt@scai.fraunhofer.de
License: MIT License
Keywords: Biological Expression Language,BEL,Systems Biology,Networks Biology,InterPro
Platform: UNKNOWN
Classifier: Development Status :: 4 - Beta
Classifier: Environment :: Console
Classifier: Intended Audience :: Developers
Classifier: Intended Audience :: Science/Research
Classifier: License :: OSI Approved :: MIT License
Classifier: Operating System :: OS Independent
Classifier: Programming Language :: Python
Classifier: Programming Language :: Python :: 3.6
Classifier: Programming Language :: Python :: 3.7
Classifier: Topic :: Scientific/Engineering :: Bio-Informatics
Requires-Dist: networkx (>=2.1)
Requires-Dist: pybel (>=0.13.0)
Requires-Dist: bio2bel (<0.3.0,>=0.2.0)
Requires-Dist: compath-utils
Requires-Dist: click
Requires-Dist: sqlalchemy
Requires-Dist: tqdm
Requires-Dist: pandas
Provides-Extra: docs
Requires-Dist: flask ; extra == 'docs'
Requires-Dist: flask-admin ; extra == 'docs'
Requires-Dist: sphinx ; extra == 'docs'
Requires-Dist: sphinx-rtd-theme ; extra == 'docs'
Requires-Dist: sphinx-click ; extra == 'docs'
Provides-Extra: web
Requires-Dist: flask ; extra == 'web'
Requires-Dist: flask-admin ; extra == 'web'
